airgym/__init__.py
airgym/spaces_definition.py
airgym/x_plane_connect.py
airgym/envs/__init__.py
airgym/envs/airgym_v1.py
airgym-0.0.5.dist-info/LICENSE
airgym-0.0.5.dist-info/METADATA
airgym-0.0.5.dist-info/WHEEL
airgym-0.0.5.dist-info/entry_points.txt
airgym-0.0.5.dist-info/top_level.txt
airgym-0.0.5.dist-info/RECORD
