Metadata-Version: 2.1
Name: airgym
Version: 0.0.5
Summary: OpenAI Gym environment for training reinforcement learning agents on an XPlane simulator
Home-page: https://github.com/zacjiker/airgym
Author: SAUVECANNE, Baptiste
Author-email: contact@baptistesauvecanne.fr
License: GPL-3.0
Keywords: openai,gym,xplane,reinforcement learning,rl,environment,ai,artificial intelligence,machine learning,ml
Classifier: Development Status :: 3 - Alpha
Classifier: Intended Audience :: Developers
Classifier: License :: OSI Approved :: GNU General Public License v3 (GPLv3)
Classifier: Programming Language :: Python :: 3
Classifier: Programming Language :: Python :: 3.6
Classifier: Programming Language :: Python :: 3.7
Classifier: Programming Language :: Python :: 3.8
Classifier: Programming Language :: Python :: 3.9
Requires-Python: >=3.6
License-File: LICENSE
Requires-Dist: gym (==0.21.0)
Requires-Dist: scipy (==1.10.1)
